MANIFEST.in
setup.py
pluzz/__init__.py
pluzz/pluzz.py
pluzz/qtpluzz.py
pluzz/i18n/en_UK/LC_MESSAGES/pypluzz.mo
pluzz/i18n/en_UK/LC_MESSAGES/pypluzz.po
pluzz/i18n/en_US/LC_MESSAGES/pypluzz.mo
pluzz/i18n/en_US/LC_MESSAGES/pypluzz.po
pluzz/i18n/en_US/LC_MESSAGES/pypluzz.pot
pluzz/i18n/fr_FR/LC_MESSAGES/pypluzz.mo
pluzz/i18n/fr_FR/LC_MESSAGES/pypluzz.po
pypluzz.egg-info/PKG-INFO
pypluzz.egg-info/SOURCES.txt
pypluzz.egg-info/dependency_links.txt
pypluzz.egg-info/entry_points.txt
pypluzz.egg-info/not-zip-safe
pypluzz.egg-info/requires.txt
pypluzz.egg-info/top_level.txt